cli_chronicler/__init__.py
cli_chronicler/config.yaml
cli_chronicler/main.py
cli_chronicler/sql/hours_by_category.sql
cli_chronicler/sql/open_punches.sql
cli_chronicler/src/__init__.py
cli_chronicler/src/reporter.py
cli_chronicler/src/utils.py
cli_chronicler-0.6.3.dist-info/LICENSE
cli_chronicler-0.6.3.dist-info/METADATA
cli_chronicler-0.6.3.dist-info/WHEEL
cli_chronicler-0.6.3.dist-info/entry_points.txt
cli_chronicler-0.6.3.dist-info/top_level.txt
cli_chronicler-0.6.3.dist-info/RECORD
