Metadata-Version: 2.1
Name: cli_chronicler
Version: 0.6.3
Summary: A command line app for keeping track of project/work times.
License-File: LICENSE
